pymp4/__init__.py
pymp4/adapters.py
pymp4/cli.py
pymp4/exceptions.py
pymp4/parser.py
pymp4/subconstructs.py
pymp4/tools/__init__.py
pymp4/util.py
pymp4x-2.1.0.dist-info/LICENSE
pymp4x-2.1.0.dist-info/METADATA
pymp4x-2.1.0.dist-info/WHEEL
pymp4x-2.1.0.dist-info/entry_points.txt
pymp4x-2.1.0.dist-info/RECORD
